gce_submit_metric
