Metadata-Version: 1.1
Name: gce-submit-metric
Version: 1.1.0
Summary: Submit a metric for GCE instances to Stackdriver
Home-page: https://github.com/mioi/gce-submit-metric
Author: Mioi Hanaoka
Author-email: mioihanaoka@gmail.com
License: UNKNOWN
Keywords: Cloud Infrastructure
Platform: UNKNOWN
Classifier: Development Status :: 2 - Pre-Alpha
Classifier: Intended Audience :: System Administrators
Classifier: Operating System :: POSIX :: Linux
Classifier: Programming Language :: Python
Classifier: Programming Language :: Python :: 2.7
Classifier: Topic :: System :: Distributed Computing
Classifier: Topic :: System :: Systems Administration
